{"maps/arid/forest-1.json/entities/245/settings/condAnims/0/interact/hoverText":{"orig":"Search Targets","text":"Поиск целей"},"maps/arid/forest-1.json/entities/245/settings/condAnims/0/interact/event/1/text":{"orig":"Locate Targets in Area.","text":"Найдите цели в области."},"maps/arid/forest-1.json/entities/245/settings/condAnims/1/interact/hoverText":{"orig":"Activate","text":"Активировать"},"maps/arid/forest-1.json/entities/510/settings/event/9/message":{"orig":"Now we enter the realm of \\c[3]Ebony Forest\\c[0]!","text":"Теперь мы входим во владения \\c[3]Эбонитового леса\\c[0]!"},"maps/arid/forest-1.json/entities/510/settings/event/10/message":{"orig":"As expected...\\. it's full of trees.","text":"Как и ожидалось...\\. он полон деревьев."},"maps/arid/forest-1.json/entities/510/settings/event/11/message":{"orig":"[nods]","text":"[кивает]"},"maps/arid/forest-1.json/entities/510/settings/event/12/message":{"orig":"Yet there are no evil wolves in this forest. It's just viruses as always.","text":"Однако в этом лесу нет злых волков. Всего лишь вирусы, как и обычно."},"maps/arid/forest-1.json/entities/510/settings/event/13/message":{"orig":"...","text":"..."},"maps/arid/forest-1.json/entities/510/settings/event/14/message":{"orig":"Also no bugs. I'm sure Emilie would be glad to hear that.","text":"Жуков тоже нет. Я уверен, что Эмили была бы рада это услышать."},"maps/arid/forest-1.json/entities/510/settings/event/15/message":{"orig":"...","text":"..."},"maps/arid/forest-1.json/entities/510/settings/event/16/message":{"orig":"Seriously, though.\\. Emilie and her fear of bugs...\\. I don't quite get it.","text":"Если серьёзно.\\. Эмили и её страх перед жуками...\\. Я не совсем понимаю."},"maps/arid/forest-1.json/entities/510/settings/event/17/message":{"orig":"She made such a huge deal out of the Faj'ro Temple boss. That giant moth, right?","text":"Она переборола себя с этим боссом храма Фай'ро. Ну, этот гигантский мотылёк."},"maps/arid/forest-1.json/entities/510/settings/event/18/message":{"orig":"[nods]","text":"[кивает]"},"maps/arid/forest-1.json/entities/510/settings/event/19/message":{"orig":"But when I asked her about the midboss...\\. that antlion?\\. No problem there!","text":"Но когда я спросил её о промежуточном боссе...\\. тот муравьиный лев?\\. С этим проблем не возникло!"},"maps/arid/forest-1.json/entities/510/settings/event/20/message":{"orig":"...How?","text":"...Как?"},"maps/arid/forest-1.json/entities/510/settings/event/21/message":{"orig":"Yeah, apparently it's all good because it's \"slow\" and \"stuck in the sand\".","text":"Ага, видимо, всё нормально, потому что он \"медленный\" и \"застрял в песке\"."},"maps/arid/forest-1.json/entities/510/settings/event/22/message":{"orig":"Personally, I thought the antlion was much higher on the scary scale.","text":"Лично мне кажется, что муравьиный лев был намного страшнее."},"maps/arid/forest-1.json/entities/510/settings/event/23/message":{"orig":"[nods]","text":"[кивает]"},"maps/arid/forest-1.json/entities/510/settings/event/24/message":{"orig":"Right? Well, that's Emilie for you.","text":"Так ведь? Ну, в этом вся Эмили."},"maps/arid/forest-1.json/entities/510/settings/event/25/message":{"orig":"Let's continue!","text":"Давай продолжим!"},"maps/arid/forest-1.json/entities/510/settings/event/30/message":{"orig":"Over there is a pretty interesting spot!","text":"Там есть довольно интересное место!"},"maps/arid/forest-1.json/entities/510/settings/event/34/task":{"orig":"Talk to Lukas in \\c[3]Vermillion Wasteland - Ebony Forest\\c[0] to proceed with his tour.","text":"Поговорите с Лукасом в \\c[3]Пустоши Вермиллион - Эбонитовый лес\\c[0], чтобы продолжить его экскурсию."},"maps/arid/forest-1.json/entities/511/settings/npcStates/0/event/quest/6/message":{"orig":"I call this here the \\c[3]field of the indecisive flowers\\c[0].","text":"Я называю это полем \\c[3]нерешительных цветов\\c[0]."},"maps/arid/forest-1.json/entities/511/settings/npcStates/0/event/quest/7/message":{"orig":"...?","text":"...?"},"maps/arid/forest-1.json/entities/511/settings/npcStates/0/event/quest/8/message":{"orig":"Indecisive because they can't decide on what height to grow.","text":"Нерешительные, потому что они не могут решить, до какой высоты расти."},"maps/arid/forest-1.json/entities/511/settings/npcStates/0/event/quest/9/message":{"orig":"I mean just look at them. Some are stuck on ground level, others several meters high.","text":"Я имею в виду, просто посмотри на них. Некоторые застряли на уровне земли, а другие высотой в несколько метров."},"maps/arid/forest-1.json/entities/511/settings/npcStates/0/event/quest/10/message":{"orig":"...","text":"..."},"maps/arid/forest-1.json/entities/511/settings/npcStates/0/event/quest/11/message":{"orig":"...Why?","text":"...Почему?"},"maps/arid/forest-1.json/entities/511/settings/npcStates/0/event/quest/12/message":{"orig":"Look, I can't even explain a lake to you, so what do you expect now?","text":"Слушай, я даже не могу объяснить тебе насчёт озера, так чего ты ждёшь сейчас?"},"maps/arid/forest-1.json/entities/511/settings/npcStates/0/event/quest/13/message":{"orig":"...","text":"..."},"maps/arid/forest-1.json/entities/511/settings/npcStates/0/event/quest/15/message":{"orig":"Anyway, those flowers are awfully convenient for an elaborate jumping path, don't you think?","text":"В любом случае, эти цветы очень удобно подходят для замысловатого пути для прыжков, не так ли?"},"maps/arid/forest-1.json/entities/511/settings/npcStates/0/event/quest/16/message":{"orig":"[nods]","text":"[кивает]"},"maps/arid/forest-1.json/entities/511/settings/npcStates/0/event/quest/17/message":{"orig":"I mean this wouldn't be CrossWorlds without unlikely jumping paths literally everywhere.","text":"В том смысле, что это был бы не CrossWorlds без этих прыжков буквально повсюду."},"maps/arid/forest-1.json/entities/511/settings/npcStates/0/event/quest/18/message":{"orig":"The only thing I'm missing here is the treasure chest to collect.","text":"Единственное, чего мне здесь не хватает - это сундука с сокровищами, который нужно собрать."},"maps/arid/forest-1.json/entities/511/settings/npcStates/0/event/quest/19/message":{"orig":"So I suppose we both can guess when those flowers will come into play.","text":"Так что, полагаю, что мы можем только догадываться, когда эти цветы смогут понадобиться."},"maps/arid/forest-1.json/entities/511/settings/npcStates/0/event/quest/20/message":{"orig":"...","text":"..."},"maps/arid/forest-1.json/entities/511/settings/npcStates/0/event/quest/27/message":{"orig":"Enough of this forest. Let's go back to the lake. There is one more location I want to show you.","text":"Хватит этого леса. Давай вернёмся к озеру. Есть ещё одно место, которое я хочу тебе показать."},"maps/arid/forest-1.json/entities/511/settings/npcStates/0/event/quest/28/message":{"orig":"...!","text":"...!"},"maps/arid/forest-1.json/entities/511/settings/npcStates/0/event/quest/31/task":{"orig":"Head back to \\c[3]Vermillion Wasteland - Crimson Lake\\c[0] to proceed with Lukas' tour.","text":"Возвращайтесь в \\c[3]Пустошь Вермиллион - Алое озеро\\c[0], чтобы продолжить экскурсию Лукаса."},"maps/arid/forest-1.json/entities/512/settings/event/0/message":{"orig":"Is there really nothing else you'd like to do?","text":"Неужели тебе правда больше ничем не хочется заняться?"},"maps/arid/forest-1.json/entities/512/settings/event/1/message":{"orig":"...","text":"..."},"maps/arid/forest-1.json/entities/512/settings/event/2/message":{"orig":"Lea...?","text":"Лея...?"},"maps/arid/forest-1.json/entities/514/settings/event/0/message":{"orig":"Hah, told you we'd be jumping over these flowers.","text":"Ха, говорил же тебе, что мы будем прыгать по этим цветам."},"maps/arid/forest-1.json/entities/514/settings/event/1/message":{"orig":"...","text":"..."},"maps/arid/forest-1.json/entities/514/settings/event/2/message":{"orig":"...","text":"..."},"maps/arid/forest-1.json/entities/538/settings/blockEvent/4/message":{"orig":"Come on, Lea. Let's call it a day.","text":"Да ладно, Лея. Давай закончим на этом."},"maps/arid/forest-1.json/entities/538/settings/blockEvent/5/message":{"orig":"There's still time for the trial building tomorrow.","text":"Завтра ещё будет время для пробного здания."},"maps/arid/forest-1.json/entities/538/settings/blockEvent/6/message":{"orig":"...","text":"..."},"maps/arid/forest-1.json/entities/541/settings/event/6/message":{"orig":"Okay, here we go again...","text":"Хорошо, опять то же самое..."},"maps/arid/forest-1.json/entities/541/settings/event/14/message":{"orig":"Huh?","text":"Хмм?"},"maps/arid/forest-1.json/entities/541/settings/event/25/message":{"orig":"Enemies already?\\. Let us enter the damn building first!","text":"Враги, уже? Дайте сначала хоть войти в это чёртово здание!"},"maps/arid/forest-1.json/entities/560/settings/event/13/message":{"orig":"Finally...","text":"Наконец-то..."},"maps/arid/forest-1.json/entities/560/settings/event/14/message":{"orig":"...","text":"..."},"maps/arid/forest-1.json/entities/560/settings/event/17/message":{"orig":"So...\\. should we enter?","text":"Так...\\. мы должны войти?"},"maps/arid/forest-1.json/entities/560/settings/event/19/message":{"orig":"...","text":"..."},"maps/arid/forest-1.json/entities/560/settings/event/20/message":{"orig":"Honestly, I don't have a good feeling about this.","text":"Честно говоря, у меня нехорошее предчувствие по этому поводу."},"maps/arid/forest-1.json/entities/560/settings/event/21/message":{"orig":"There will probably be more high-level enemies in there.","text":"Там, вероятно, будет ещё больше врагов высокого уровня."},"maps/arid/forest-1.json/entities/560/settings/event/22/thenStep/0/message":{"orig":"Not that this matters much for you, but still...\\. with you being like this today...","text":"Не то чтобы это было большой проблемой для тебя, но всё же...\\. в таком состоянии, как у тебя сегодня..."},"maps/arid/forest-1.json/entities/560/settings/event/22/elseStep/0/message":{"orig":"And with you being like this today...","text":"А в таком состоянии, как у тебя сегодня..."},"maps/arid/forest-1.json/entities/560/settings/event/23/message":{"orig":"...","text":"..."},"maps/arid/forest-1.json/entities/560/settings/event/24/message":{"orig":"Should we continue another time?\\. There is no reason to rush this, right?","text":"Может, продолжим в другой раз?\\. Нет причин торопиться, верно?"},"maps/arid/forest-1.json/entities/560/settings/event/25/message":{"orig":"...","text":"..."},"maps/arid/forest-1.json/entities/560/settings/event/26/message":{"orig":"...","text":"..."},"maps/arid/forest-1.json/entities/560/settings/event/27/message":{"orig":"It really would help if you'd respond... at all.","text":"Было бы неплохо, если бы ты реагировала... хоть как-то."},"maps/arid/forest-1.json/entities/560/settings/event/28/message":{"orig":"I mean...\\. I understand why you'd feel down in a situation like this.","text":"То есть...\\. Я понимаю, почему ты чувствуешь себя подавленно в таких ситуациях."},"maps/arid/forest-1.json/entities/560/settings/event/29/message":{"orig":"But...\\. things don't have to stay that way.","text":"Но...\\. долго так продолжаться не может."},"maps/arid/forest-1.json/entities/560/settings/event/30/message":{"orig":"I'm sure we'll find a way out.\\. Out of this place...\\. out of this game...","text":"Я уверен, что мы найдём выход.\\. Из этого места...\\. из этой игры..."},"maps/arid/forest-1.json/entities/560/settings/event/31/message":{"orig":"...","text":"..."},"maps/arid/forest-1.json/entities/560/settings/event/32/message":{"orig":"We just shouldn't lose hope...","text":"Мы просто не должны терять надежду..."},"maps/arid/forest-1.json/entities/560/settings/event/35/message":{"orig":"...","text":"..."},"maps/arid/forest-1.json/entities/560/settings/event/36/message":{"orig":"....Lea?","text":"....Лея?"},"maps/arid/forest-1.json/entities/560/settings/event/45/message":{"orig":"...","text":"..."},"maps/arid/forest-1.json/entities/560/settings/event/47/message":{"orig":"... Oh...","text":"...Ох..."},"maps/arid/forest-1.json/entities/560/settings/event/48/message":{"orig":"Oh Junge...","text":"Oh Junge (Боже)..."},"maps/arid/forest-1.json/entities/561/settings/event/6/message":{"orig":"Here we are. For real this time.","text":"Вот мы и пришли. На этот раз по-настоящему."},"maps/arid/forest-1.json/entities/561/settings/event/7/message":{"orig":"...","text":"..."},"maps/arid/forest-1.json/entities/561/settings/event/14/thenStep/0/message":{"orig":"They might throw another high level enemy at us, so I'll be counting on your support in that case.","text":"Они могут бросить на нас очередного врага высокого уровня, так что в этом случае, я буду рассчитывать на твою поддержку."},"maps/arid/forest-1.json/entities/561/settings/event/14/elseStep/0/message":{"orig":"They might throw another high level enemy at us, so better keep your guard up.","text":"Они могут бросить на нас очередного врага высокого уровня, так что лучше будь наготове."},"maps/arid/forest-1.json/entities/561/settings/event/15/message":{"orig":"[nods]","text":"[кивает]"},"maps/arid/forest-1.json/entities/561/settings/event/16/message":{"orig":"Can't wait to see what kind of room they'll show us this time.","text":"Не могу дождаться, чтобы увидеть, какую комнату они покажут нам на этот раз."},"maps/arid/forest-1.json/entities/568/settings/event/0/message":{"orig":"Secret laser bridge!! Yaay!","text":"Секретный лазерный мост!! Ура!"},"maps/arid/forest-1.json/entities/570/settings/dialog/0/text":{"orig":"Must leave...","text":"Должен выйти..."},"maps/arid/forest-1.json/entities/570/settings/dialog/1/text":{"orig":"Leave...","text":"Выйти..."},"maps/arid/forest-1.json/entities/570/settings/dialog/2/text":{"orig":"Please let me leave...","text":"Пожалуйста, дайте мне уйти..."}}
