{"maps/autumn-fall/path-03.json/entities/4/settings/event/1/text":{"orig":"Access denied","text":"Отказано в доступе"},"maps/autumn-fall/path-03.json/entities/589/settings/event/1/text":{"orig":"Blocked","text":"Заблокировано"},"maps/autumn-fall/path-03.json/entities/601/settings/blockEvent/2/message":{"orig":"Uhm...\\. Lea?","text":"Эмм...\\. Лея?"},"maps/autumn-fall/path-03.json/entities/601/settings/blockEvent/3/message":{"orig":"I think C'tron and the others are waiting for you at the \\c[3]First Scholar HQ\\c[0], correct?","text":"Я думаю, что Ци'трон и другие ждут тебя в \\c[3]штабе Первоучёных\\c[0], так ведь?"},"maps/autumn-fall/path-03.json/entities/601/settings/blockEvent/4/message":{"orig":"You probably should go there before heading to \\c[3]Sapphire Ridge\\c[0].","text":"Ты, вероятно, должна заглянуть туда, прежде чем отправиться в \\c[3]Сапфировый край\\c[0]."},"maps/autumn-fall/path-03.json/entities/601/settings/blockEvent/5/message":{"orig":"...","text":"..."},"maps/autumn-fall/path-03.json/entities/699/settings/interact/hoverText":{"orig":"\\i[arrow-e] Tunnel to \\v[area.forest.name]\n\\i[arrow-w] \\v[area.jungle.name]\n","text":"\\i[arrow-e] тоннель в Сапфировый край\n\\i[arrow-w] Сад Гайи"},"maps/autumn-fall/path-03.json/entities/704/settings/npcStates/0/event/2/message":{"orig":"Yo, what's up?","text":"Йо, как дела?"},"maps/autumn-fall/path-03.json/entities/704/settings/npcStates/0/event/3/thenStep/0/message":{"orig":"I see you got the \\c[3]\\v[item.410.name]\\c[0] with you! Nice, nice!","text":"Я вижу, что у тебя есть \\c[3]Тень звезды\\c[0]! Круто, круто!"},"maps/autumn-fall/path-03.json/entities/704/settings/npcStates/0/event/3/thenStep/1/message":{"orig":"Well then, good luck in \\c[3]Sapphire Ridge\\c[0]! Beware of bugs!","text":"Тогда удачи в \\c[3]Сапфировом крае\\c[0]! Остерегайся жуков!"},"maps/autumn-fall/path-03.json/entities/704/settings/npcStates/0/event/3/thenStep/2/thenStep/1/message":{"orig":"Wait... What was that?","text":"Подожди... что он сказал?"},"maps/autumn-fall/path-03.json/entities/704/settings/npcStates/0/event/3/elseStep/0/message":{"orig":"If you want to pass the barrier up ahead you first have to collect the \\c[3]\\v[item.410.name]\\c[0].","text":"Если ты хочешь пройти через барьер впереди, то сначала должна получить \\c[3]Тень звезды\\c[0]."},"maps/autumn-fall/path-03.json/entities/704/settings/npcStates/0/event/3/elseStep/1/message":{"orig":"You get it at the end of the \\c[3]Grand Krys'kajo\\c[0] dungeon in \\c[3]Gaia's Garden\\c[0].","text":"Ты получишь её в конце подземелья \\c[3]Гранд Крис'кайо\\c[0] в \\c[3]Саду Гайи\\c[0]."},"maps/autumn-fall/path-03.json/entities/704/settings/npcStates/0/event/3/elseStep/2/message":{"orig":"If you've already finished the dungeon... just revisit the \\c[3]final boss room\\c[0]. I'm sure you'll find the shades somewhere in there.","text":"Если ты уже закончила это подземелье... просто посети \\c[3]комнату с последним боссом\\c[0]. Я уверен, что ты найдёшь Тень где-то там."},"maps/autumn-fall/path-03.json/entities/704/settings/npcStates/0/event/3/elseStep/3/message":{"orig":"...!","text":"...!"}}
