{"maps/heat/path-01-entrance.json/entities/8/settings/interact/hoverText":{"orig":"\\i[arrow-w] Road to \\v[area.heat-village.name]\n\\i[arrow-e] Railway to \\v[area.bergen.name]","text":"\\i[arrow-w] дорога к Ба'кии Кум\n\\i[arrow-e] Рельсовая дорога к Бергену"},"maps/heat/path-01-entrance.json/entities/307/settings/dialog/0/text":{"orig":"We finally made it!","text":"Мы наконец сделали это!"},"maps/heat/path-01-entrance.json/entities/307/settings/dialog/1/text":{"orig":"And after the freezing cold in \\v[area.bergen.name] the heat is very welcome.","text":"И после морозов в Бергене жара неплохо заходит."},"maps/heat/path-01-entrance.json/entities/307/settings/dialog/2/text":{"orig":"Well that's easy for you to say. I'm already sweating...","text":"Ну, это тебе легко говорить. Я уже потею..."},"maps/heat/path-01-entrance.json/entities/307/settings/dialog/3/text":{"orig":"Oh come on, you could just turn off the simulation of heat.","text":"Ой, перестань, ты можешь просто отключить симуляцию жары."},"maps/heat/path-01-entrance.json/entities/307/settings/dialog/4/text":{"orig":"But I don't want to break the immersion...","text":"Но я не хочу нарушать погружение..."},"maps/heat/path-01-entrance.json/entities/307/settings/dialog/5/text":{"orig":"But this is just... too hot. I might have to.","text":"Но это просто... слишком жарко. Возможно, мне всё-таки придётся."},"maps/heat/path-01-entrance.json/entities/313/settings/dialog/0/text":{"orig":"Think about it, if we could make such a device...","text":"Подумай об этом, если бы мы могли сделать такое устройство..."},"maps/heat/path-01-entrance.json/entities/313/settings/dialog/1/text":{"orig":"We would need to canvas all areas and distribute them to the Seekers.","text":"Нам нужно будет покрыть все области и распространить их среди Искателей."},"maps/heat/path-01-entrance.json/entities/313/settings/dialog/2/text":{"orig":"Let's bring this up when we meet the boss later.","text":"Давай обсудим это позже, после того, как встретимся с боссом."},"maps/heat/path-01-entrance.json/entities/313/settings/dialog/3/text":{"orig":"Sure, why not?","text":"Конечно, почему нет?"},"maps/heat/path-01-entrance.json/entities/314/settings/npcStates/0/event/2/message":{"orig":"Oh hey, Stranger.","text":"О, хей, незнакомка."},"maps/heat/path-01-entrance.json/entities/314/settings/npcStates/0/event/3/message":{"orig":"Hi!","text":"Привет!"},"maps/heat/path-01-entrance.json/entities/314/settings/npcStates/0/event/4/message":{"orig":"Your first time here?","text":"Впервые здесь?"},"maps/heat/path-01-entrance.json/entities/314/settings/npcStates/0/event/5/message":{"orig":"[nods]","text":"[кивает]"},"maps/heat/path-01-entrance.json/entities/314/settings/npcStates/0/event/6/message":{"orig":"Hehe, me too! ","text":"Хе-хе, я тоже."},"maps/heat/path-01-entrance.json/entities/314/settings/npcStates/0/event/7/message":{"orig":"I'm pretty glad that we get a breather after the \\c[3]Temple Mine\\c[0]. ","text":"Я очень рад, что мы получили передышку после \\c[3]Храм-Шахты\\c[0]."},"maps/heat/path-01-entrance.json/entities/314/settings/npcStates/0/event/8/message":{"orig":"But I can already see new enemies beyond this ravine.","text":"Но я уже вижу новых врагов за этим ущельем."},"maps/heat/path-01-entrance.json/entities/314/settings/npcStates/0/event/15/message":{"orig":"I just hope they act as cute as they look.","text":"Я просто надеюсь, что они ведут себя так же мило, как они выглядят."},"maps/heat/path-01-entrance.json/entities/314/settings/npcStates/0/event/16/message":{"orig":"...","text":"..."},"maps/heat/path-01-entrance.json/entities/315/settings/event/11/message":{"orig":"Hello, Human! You look puzzled!","text":"Привет, человек! Ты выглядишь озадаченным!"},"maps/heat/path-01-entrance.json/entities/315/settings/event/12/message":{"orig":"You entered \\c[3]Maroon Valley\\c[0], hot-sandy desert and home of us \\c[3]Shad\\c[0]!","text":"Ты вошёл в \\c[3]Бордовую долину\\c[0], горячую песчаную пустыню и дом \\c[3]шадов\\c[0]!"},"maps/heat/path-01-entrance.json/entities/315/settings/event/13/message":{"orig":"All humans welcome!","text":"Всем людям - добро пожаловать!"},"maps/heat/path-01-entrance.json/entities/315/settings/event/14/message":{"orig":"You should visit \\c[3]Ba'kii Kum\\c[0], bustling town of Shad!","text":"Ты должен посетить \\c[3]Ба'кии Кум\\c[0], шумный город шадов!"},"maps/heat/path-01-entrance.json/entities/315/settings/event/15/message":{"orig":"Has big bazaar with great offers!","text":"Там большой базар с отличными предложениями!"},"maps/heat/path-01-entrance.json/entities/315/settings/event/16/message":{"orig":"...!","text":"...!"},"maps/heat/path-01-entrance.json/entities/315/settings/event/17/message":{"orig":"Human want to know more? Talk to me!","text":"Человек хочет знать больше? Поговори со мной!"},"maps/heat/path-01-entrance.json/entities/315/settings/event/32/message":{"orig":"Bonjour, Lea!","text":"Bonjour (Привет), Лея!"},"maps/heat/path-01-entrance.json/entities/315/settings/event/33/message":{"orig":"Hi!","text":"Привет!"},"maps/heat/path-01-entrance.json/entities/315/settings/event/34/message":{"orig":"Say... are you currently free?","text":"Скажи... ты сейчас свободна?"},"maps/heat/path-01-entrance.json/entities/315/settings/event/35/message":{"orig":"I'd really like to join your party right now...\\. if you are okay with that.","text":"Я бы очень хотела присоединиться к твоей группе прямо сейчас...\\. если ты не против, конечно."},"maps/heat/path-01-entrance.json/entities/315/settings/event/36/message":{"orig":"[nods]","text":"[кивает]"},"maps/heat/path-01-entrance.json/entities/315/settings/event/37/message":{"orig":"Très bien!\\. Did you just enter Maroon Valley by any chance?","text":"Très bien (Прекрасно)!\\. Ты случайно только что не вошла в Бордовую долину?"},"maps/heat/path-01-entrance.json/entities/315/settings/event/38/message":{"orig":"[nods]","text":"[кивает]"},"maps/heat/path-01-entrance.json/entities/315/settings/event/39/message":{"orig":"Okay, I'll be there in a second!","text":"Хорошо, я буду там через секунду!"},"maps/heat/path-01-entrance.json/entities/315/settings/event/55/message":{"orig":"Thanks for waiting...","text":"Спасибо за ожидание..."},"maps/heat/path-01-entrance.json/entities/315/settings/event/59/message":{"orig":"Did that birdman over there talk to you as well?","text":"Тот человек-птица там тоже разговаривал с тобой?"},"maps/heat/path-01-entrance.json/entities/315/settings/event/60/message":{"orig":"[nods]","text":"[кивает]"},"maps/heat/path-01-entrance.json/entities/315/settings/event/61/message":{"orig":"He does that with any new player that stands around for too long, non?","text":"Он делает это с каждым новым игроком, который стоит слишком долго, не так ли?"},"maps/heat/path-01-entrance.json/entities/315/settings/event/62/message":{"orig":"I was surprised to meet a non-human race after all!","text":"Я была удивлена, встретив в конце концов нечеловеческую расу!"},"maps/heat/path-01-entrance.json/entities/315/settings/event/63/message":{"orig":"...","text":"..."},"maps/heat/path-01-entrance.json/entities/315/settings/event/67/message":{"orig":"Anyway, we should head to \\c[3]Ba'kii Kum\\c[0], right? Sounds like the next big town.","text":"В любом случае, мы должны отправиться в \\c[3]Ба'кии Кум\\c[0], верно? Похоже, это следующий большой город."},"maps/heat/path-01-entrance.json/entities/315/settings/event/68/message":{"orig":"[nods]","text":"[кивает]"},"maps/heat/path-01-entrance.json/entities/315/settings/event/69/message":{"orig":"Well then... off we go!","text":"Ну тогда... пошли!"},"maps/heat/path-01-entrance.json/entities/315/settings/event/75/task":{"orig":"Travel to \\c[3]Ba'kii Kum\\c[0] together with Emilie.","text":"Отправляйтесь в \\c[3]Ба'кии Кум\\c[0] вместе с Эмили."},"maps/heat/path-01-entrance.json/entities/316/settings/npcStates/0/event/2/message":{"orig":"Human, want to know way to \\c[3]Ba'kii Kum\\c[0]?","text":"Человек хочет узнать дорогу до \\c[3]Ба'кии Кум\\c[0]?"},"maps/heat/path-01-entrance.json/entities/316/settings/npcStates/0/event/3/0/0/message":{"orig":"[nods]","text":"[кивает]"},"maps/heat/path-01-entrance.json/entities/316/settings/npcStates/0/event/3/0/1/message":{"orig":"Easy! Human just follow this way to \\c[3]west\\c[0].","text":"Легко! Человек просто следует этим путём к \\c[3]западу\\c[0]."},"maps/heat/path-01-entrance.json/entities/316/settings/npcStates/0/event/3/0/2/message":{"orig":"You shortly need to turn \\c[3]south\\c[0], then go \\c[3]west\\c[0] again and follow way below \\c[3]arcs of rock\\c[0]!","text":"Вскоре тебе нужно повернуть \\c[3]на юг\\c[0], затем снова пройти \\c[3]на запад\\c[0] и следовать ниже \\c[3]скальных арок\\c[0]!"},"maps/heat/path-01-entrance.json/entities/316/settings/npcStates/0/event/3/0/4/message":{"orig":"You then need to turn \\c[3]north\\c[0] to reach deep abyss. Use rocks to jump over it.","text":"Затем тебе нужно повернуть \\c[3]на север\\c[0], чтобы достичь глубокой пропасти. Используй камни, чтобы перепрыгнуть через неё."},"maps/heat/path-01-entrance.json/entities/316/settings/npcStates/0/event/3/0/6/message":{"orig":"Afterwards you need to turn \\c[3]west\\c[0] again and you will reach \\c[3]Great Scar\\c[0]. Amazing view to \\c[3]Hourglass Building\\c[0].","text":"После этого тебе нужно снова повернуть \\c[3]на запад\\c[0], и ты достигнешь \\c[3]Великого шрама\\c[0]. Удивительный вид на \\c[3]Сооружение песочных часов\\c[0]."},"maps/heat/path-01-entrance.json/entities/316/settings/npcStates/0/event/3/0/7/message":{"orig":"Human continue \\c[3]west\\c[0] and will soon reach \\c[3]Ba'kii Kum\\c[0]!","text":"Человек продолжит на \\c[3]запад\\c[0] и скоро достигнет \\c[3]Ба'кии Кум\\c[0]!"},"maps/heat/path-01-entrance.json/entities/316/settings/npcStates/0/event/3/0/8/message":{"orig":"...","text":"..."},"maps/heat/path-01-entrance.json/entities/316/settings/npcStates/0/event/3/0/10/message":{"orig":"Human look confused! No problem, \\c[3]just follow signposts\\c[0].","text":"Человек выглядит растерянно! Нет проблем, \\c[3]просто следуй указателям\\c[0]."},"maps/heat/path-01-entrance.json/entities/316/settings/npcStates/0/event/3/0/11/message":{"orig":"They will point way to Ba'kii Kum!","text":"Они укажут путь в Ба'кии Кум!"},"maps/heat/path-01-entrance.json/entities/316/settings/npcStates/0/event/3/0/12/message":{"orig":"...!","text":"...!"},"maps/heat/path-01-entrance.json/entities/316/settings/npcStates/0/event/3/0/13/message":{"orig":"...","text":"..."},"maps/heat/path-01-entrance.json/entities/316/settings/npcStates/0/event/3/0/14/message":{"orig":"...","text":"..."},"maps/heat/path-01-entrance.json/entities/316/settings/npcStates/0/event/3/1/0/message":{"orig":"[shakes head]","text":"[мотает головой]"},"maps/heat/path-01-entrance.json/entities/316/settings/npcStates/0/event/3/1/1/message":{"orig":"Okay! I'm here if human has question!","text":"Ладно! Я здесь, если у человека есть вопрос!"},"maps/heat/path-01-entrance.json/entities/316/settings/npcStates/0/event/3/options/0/label":{"orig":"[yes]","text":"[да]"},"maps/heat/path-01-entrance.json/entities/316/settings/npcStates/0/event/3/options/1/label":{"orig":"[no]","text":"[нет]"}}
