{"maps/flashback/satoshi-2.json/entities/273/settings/event/11/message":{"orig":"A test environment...\\. within the Playground. ","text":"Тестовой средой...\\. в игровой зоне."},"maps/flashback/satoshi-2.json/entities/273/settings/event/12/message":{"orig":"We managed to continue our research within CrossWorlds...","text":"Нам удалось продолжить наши исследования в CrossWorlds..."},"maps/flashback/satoshi-2.json/entities/273/settings/event/13/message":{"orig":"Instatainment... never interfered.","text":"Instatainment... больше не вмешивались."},"maps/flashback/satoshi-2.json/entities/273/settings/event/14/message":{"orig":"To this day I don't know how he did it.","text":"По сей день я не знаю, как он это сделал."},"maps/flashback/satoshi-2.json/entities/273/settings/event/20/message":{"orig":"Things started within this small area of Sapphire Ridge.","text":"Всё началось в этом небольшом уголке Сапфирового края."},"maps/flashback/satoshi-2.json/entities/273/settings/event/21/message":{"orig":"However, over time we realized that a larger testing area was required for effective research.","text":"Однако, со временем мы поняли, что для эффективного исследования требовалась площадка для тестирования размером побольше."}}
